dimsdk/__init__.py
dimsdk/facebook.py
dimsdk/messenger.py
dimsdk/packer.py
dimsdk/processor.py
dimsdk/twins.py
dimsdk/core/__init__.py
dimsdk/core/barrack.py
dimsdk/core/compress_keys.py
dimsdk/core/compressor.py
dimsdk/core/delegate.py
dimsdk/core/packer.py
dimsdk/core/processor.py
dimsdk/core/transceiver.py
dimsdk/cpu/__init__.py
dimsdk/cpu/base.py
dimsdk/cpu/commands.py
dimsdk/cpu/contents.py
dimsdk/cpu/creator.py
dimsdk/cpu/customized.py
dimsdk/dkd/__init__.py
dimsdk/dkd/factory.py
dimsdk/dkd/proc.py
dimsdk/mkm/__init__.py
dimsdk/mkm/bot.py
dimsdk/mkm/delegate.py
dimsdk/mkm/entity.py
dimsdk/mkm/group.py
dimsdk/mkm/station.py
dimsdk/mkm/user.py
dimsdk/mkm/utils.py
dimsdk/msg/__init__.py
dimsdk/msg/instant_delegate.py
dimsdk/msg/instant_packer.py
dimsdk/msg/reliable_delegate.py
dimsdk/msg/reliable_packer.py
dimsdk/msg/secure_delegate.py
dimsdk/msg/secure_packer.py
dimsdk/msg/utils.py
dimsdk-2.3.4.dist-info/LICENSE
dimsdk-2.3.4.dist-info/METADATA
dimsdk-2.3.4.dist-info/WHEEL
dimsdk-2.3.4.dist-info/top_level.txt
dimsdk-2.3.4.dist-info/RECORD
