Metadata-Version: 2.1
Name: dimsdk
Version: 2.3.4
Summary: Decentralized Instant Messaging SDK
Home-page: https://github.com/dimchat/sdk-py
Author: Albert Moky
Author-email: albert.moky@gmail.com
License: MIT
Classifier: Programming Language :: Python :: 3
Classifier: License :: OSI Approved :: MIT License
Classifier: Operating System :: OS Independent
License-File: LICENSE
Requires-Dist: dimp (>=2.3.3)
